corresp/__init__.py
corresp/evaluation/__init__.py
corresp/evaluation/calc_pck.py
corresp/kitti/__init__.py
corresp/kitti/read_disp_kitti.py
corresp/kitti/read_flow_kitti.py
corresp/sintel/__init__.py
corresp/sintel/read_flow_sintel.py
corresp/verts/__init__.py
corresp/verts/find_verts.py
corresp/verts/flatten_verts.py
corresp/verts/flow2verts.py
corresp/verts/mask_verts.py
corresp/verts/rescale_verts.py
corresp/verts/verts2flow.py
corresp/visualizations/__init__.py
corresp/visualizations/viz_dense.py
corresp/visualizations/viz_flow.py
corresp/visualizations/viz_verts.py
corresp-0.1.1.dist-info/DESCRIPTION.rst
corresp-0.1.1.dist-info/METADATA
corresp-0.1.1.dist-info/RECORD
corresp-0.1.1.dist-info/WHEEL
corresp-0.1.1.dist-info/metadata.json
corresp-0.1.1.dist-info/top_level.txt
tests/__init__.py
tests/test_find_verts.py
tests/test_utils.py
tests/test_verts2flow.py
