Metadata-Version: 2.0
Name: corresp
Version: 0.1.1
Summary: Python tools datasets with dense correspondences.
Home-page: http://github.com/yuyu2172/corresp
Author: Yusuke Niitani
Author-email: yuyuniitani@gmail.com
License: MIT
Platform: UNKNOWN
Requires-Dist: imageio
Requires-Dist: matplotlib (>=1.5.1)
Requires-Dist: numpy (>=1.11)
Requires-Dist: scikit-image (>=0.12.3)
Requires-Dist: scikit-learn
